[
  {
    "exercise_name": "grocery-shopping",
    "started_at": 1755533178.250054,
    "completed_at": 1755533178.760713,
    "comments": [
      "Great work! You have successfully used `git add` and `git commit` to modify the shopping list! Keep it up!"
    ],
    "status": "Completed"
  },
  {
    "exercise_name": "stage-fright",
    "started_at": 1755532914.915558,
    "completed_at": 1755532915.277544,
    "comments": [
      "Great work! You have successfully checked in all the actors!"
    ],
    "status": "Completed"
  },
  {
    "exercise_name": "under-control",
    "started_at": 1755532517.837605,
    "completed_at": 1755532518.124369,
    "comments": [
      "You successfully used git init to initialize this folder as a Git repository!"
    ],
    "status": "Completed"
  },
  {
    "exercise_name": "remote-control",
    "started_at": 1755688655.044702,
    "completed_at": 1755688732.267557,
    "comments": [
      "Great work setting up a public remote repository!"
    ],
    "status": "Completed"
  },
  {
    "exercise_name": "link-me",
    "started_at": 1755688926.730218,
    "completed_at": 1755688927.085024,
    "comments": [
      "Wrong 'upstream' remote URL"
    ],
    "status": "Incomplete"
  },
  {
    "exercise_name": "link-me",
    "started_at": 1755689013.40918,
    "completed_at": 1755689013.476264,
    "comments": [
      "Great work with using git remote to add an upstream remote!"
    ],
    "status": "Completed"
  },
  {
    "exercise_name": "push-over",
    "started_at": 1755689456.079174,
    "completed_at": 1755689457.142838,
    "comments": [
      "Great work pushing changes to the remote!"
    ],
    "status": "Completed"
  },
  {
    "exercise_name": "ignoring-somethings",
    "started_at": 1755690149.96691,
    "completed_at": 1755690151.703737,
    "comments": [
      "You are not ignoring runaway.txt. Find where the file is and fix that."
    ],
    "status": "Incomplete"
  },
  {
    "exercise_name": "ignoring-somethings",
    "started_at": 1755690384.04474,
    "completed_at": 1755690385.518368,
    "comments": [
      "Great work using .gitignore!"
    ],
    "status": "Completed"
  },
  {
    "exercise_name": "fork-repo",
    "started_at": 1755691091.263072,
    "completed_at": 1755691093.716992,
    "comments": [
      "Great work creating a fork with Github!"
    ],
    "status": "Completed"
  },
  {
    "exercise_name": "clone-repo",
    "started_at": 1755695786.287314,
    "completed_at": 1755695789.06285,
    "comments": [
      "The origin remote does not point to your fork!"
    ],
    "status": "Incomplete"
  },
  {
    "exercise_name": "fetch-and-pull",
    "started_at": 1755698349.505152,
    "completed_at": 1755698349.851153,
    "comments": [
      "Great work fetching and pulling different upstreams!"
    ],
    "status": "Completed"
  },
  {
    "exercise_name": "side-track",
    "started_at": 1756220874.001752,
    "completed_at": 1756220874.542892,
    "comments": [
      "Great work with using git branch and git checkout to fix the bugs!"
    ],
    "status": "Completed"
  },
  {
    "exercise_name": "branch-bender",
    "started_at": 1756221347.526147,
    "completed_at": 1756221347.636285,
    "comments": [
      "Great work with merging the branches in order! Try running the HTML files locally!"
    ],
    "status": "Completed"
  },
  {
    "exercise_name": "conflict-mediator",
    "started_at": 1756221629.339233,
    "completed_at": 1756221629.780543,
    "comments": [
      "You should resolve the merge by setting the print to be 'Hello Everyone and World!'",
      "Reset the repository using \"gitmastery progress reset\" and start again"
    ],
    "status": "Incomplete"
  }
]